taientsdk/__init__.py
taientsdk/taient_client.py
taientsdk-0.0.13.dist-info/METADATA
taientsdk-0.0.13.dist-info/WHEEL
taientsdk-0.0.13.dist-info/licenses/LICENSE
taientsdk-0.0.13.dist-info/RECORD
