Metadata-Version: 2.4
Name: taientsdk
Version: 0.0.13
Summary: taient sdk for python
Project-URL: Homepage, https://gitee.com/radiumweilei/taientsdk
Project-URL: Issues, https://gitee.com/radiumweilei/taientsdk/issues
Author-email: radium <weilei@taient.com>
License-Expression: MIT
License-File: LICENSE
Classifier: Operating System :: OS Independent
Classifier: Programming Language :: Python :: 3
Requires-Python: >=3.10
Requires-Dist: dotenv>=0.9.9
Requires-Dist: requests>=2.25.0
